taomn/__init__.py
taomn/configuration.py
taomn/display.py
taomn/elements/__init__.py
taomn/elements/network.py
taomn/elements/service.py
taomn/elements/volume.py
taomn/environments.py
taomn/taomn.py
taomn-0.5.4.dist-info/entry_points.txt
taomn-0.5.4.dist-info/WHEEL
taomn-0.5.4.dist-info/METADATA
taomn-0.5.4.dist-info/RECORD
