Metadata-Version: 2.1
Name: taomn
Version: 0.5.4
Summary: Quickstart your Tao masternode
Home-page: https://tao.network
License: GPL-3.0+
Keywords: tao,blockchain,masternode,node
Author: Bryce Weiner
Author-email: bryce@tao.network
Requires-Python: >=3.5,<4.0
Classifier: License :: OSI Approved :: GNU General Public License v3 or later (GPLv3+)
Classifier: Programming Language :: Python :: 3
Classifier: Programming Language :: Python :: 3.5
Classifier: Programming Language :: Python :: 3.6
Classifier: Programming Language :: Python :: 3.7
Classifier: Programming Language :: Python :: 3.8
Requires-Dist: click (>=7.0,<8.0)
Requires-Dist: clint (>=0.5.1,<0.6.0)
Requires-Dist: docker (>=3.5.0,<4.0.0)
Requires-Dist: pastel (>=0.1.0,<0.2.0)
Requires-Dist: python-slugify (>=1.2,<2.0)
Project-URL: Documentation, https://docs.tao.network/masternode/taomn/
Project-URL: Repository, https://github.com/Tao-Network/taomn
